prometheus_test/__init__.py
prometheus_test/data.py
prometheus_test/runner.py
prometheus_test/utils.py
prometheus_test/workers.py
prometheus_test-0.1.10.dist-info/METADATA
prometheus_test-0.1.10.dist-info/WHEEL
prometheus_test-0.1.10.dist-info/top_level.txt
prometheus_test-0.1.10.dist-info/RECORD
