Metadata-Version: 2.4
Name: prometheus-test
Version: 0.1.10
Summary: Test framework for Prometheus tasks
Author: Laura Abro
Requires-Python: >=3.8
Requires-Dist: requests>=2.25.0
Requires-Dist: python-dotenv>=0.19.0
Requires-Dist: pymongo>=4.0.0
Requires-Dist: PyYAML>=6.0.0
Requires-Dist: typing-extensions>=4.0.0
Dynamic: author
Dynamic: description
Dynamic: description-content-type
Dynamic: requires-dist
Dynamic: requires-python
Dynamic: summary
